Metadata-Version: 2.1
Name: pysong
Version: 0.0.3
Summary: A package providing data structures for representing symbolic musical scores
Home-page: https://github.com/eraoul/pysong
Author: Eric Nichols
Author-email: epnichols@gmail.com
License: UNKNOWN
Platform: UNKNOWN
Classifier: Programming Language :: Python :: 3
Classifier: License :: OSI Approved :: MIT License
Classifier: Operating System :: OS Independent
